search_me/.engines/.domains
search_me/.engines/.formats
search_me/.engines/.languages
search_me/.engines/.params
search_me/.engines/.pass
search_me/.engines/.regex
search_me/.engines/.salt
search_me/.engines/.useragents
search_me/.osint/.code
search_me/.osint/.dorks
search_me/.osint/.gov
search_me/.osint/.main
search_me/.osint/.swap
search_me/__init__.py
search_me/balancers.py
search_me/engines.py
search_me/exceptions.py
search_me/models.py
search_me/osint.py
search_me/services.py
search_me/storage.py
search_me/tools.py
search_me-3.2.0.dist-info/LICENSE
search_me-3.2.0.dist-info/METADATA
search_me-3.2.0.dist-info/WHEEL
search_me-3.2.0.dist-info/RECORD
