Metadata-Version: 2.1
Name: search-me
Version: 3.2.0
Summary: Search in Google, Bing, Brave, Mojeek, Moose, Yahoo, Searx
License: MIT
Keywords: google,bing,brave,mojeek,moose,yahoo,searx,async,async search,aiohttp,web search,async scraper,osint
Author: Michael R. Kisel
Author-email: aioboy@yandex.com
Maintainer: Michael R. Kisel
Maintainer-email: aioboy@yandex.com
Requires-Python: >=3.8,<3.13
Classifier: Development Status :: 5 - Production/Stable
Classifier: Framework :: AsyncIO
Classifier: Framework :: aiohttp
Classifier: Intended Audience :: Developers
Classifier: Intended Audience :: End Users/Desktop
Classifier: Intended Audience :: Information Technology
Classifier: Intended Audience :: Science/Research
Classifier: Intended Audience :: System Administrators
Classifier: License :: OSI Approved :: MIT License
Classifier: Operating System :: OS Independent
Classifier: Programming Language :: Python
Classifier: Programming Language :: Python :: 3
Classifier: Programming Language :: Python :: 3.8
Classifier: Programming Language :: Python :: 3.9
Classifier: Programming Language :: Python :: 3.10
Classifier: Programming Language :: Python :: 3.11
Classifier: Programming Language :: Python :: 3.12
Classifier: Topic :: Home Automation
Classifier: Topic :: Internet
Classifier: Topic :: Scientific/Engineering
Classifier: Topic :: Scientific/Engineering :: Information Analysis
Classifier: Topic :: Sociology
Classifier: Topic :: Software Development
Requires-Dist: aiohttp (<=3.10.11)
Requires-Dist: bs4 (<=0.0.1)
Requires-Dist: cryptography (<=41.0.1)
Requires-Dist: importlib_resources
Requires-Dist: jmespath (<=1.0.1)
Requires-Dist: numpy (<2.0.0)
Requires-Dist: pandas (<=2.0.3)
Requires-Dist: tabulate (<=0.9.0)
Project-URL: documentation, https://aioboy.tech/p/search-me/
Project-URL: homepage, https://pypi.org/project/search-me
Project-URL: repository, https://gitlab.com/aioboy/search-me/
